snakemake_software_deployment_plugin_conda/__init__.py
snakemake_software_deployment_plugin_conda/pinfiles.py
snakemake_software_deployment_plugin_conda-0.3.2.dist-info/METADATA
snakemake_software_deployment_plugin_conda-0.3.2.dist-info/WHEEL
snakemake_software_deployment_plugin_conda-0.3.2.dist-info/RECORD
